centigrad/__init__.py
centigrad/layer.py
centigrad/network.py
centigrad/variable.py
centigrad-0.1.3.dist-info/LICENSE
centigrad-0.1.3.dist-info/METADATA
centigrad-0.1.3.dist-info/WHEEL
centigrad-0.1.3.dist-info/top_level.txt
centigrad-0.1.3.dist-info/RECORD
